anemoi/registry/__init__.py
anemoi/registry/__main__.py
anemoi/registry/_version.py
anemoi/registry/config.yaml
anemoi/registry/configuration.py
anemoi/registry/rest.py
anemoi/registry/tasks.py
anemoi/registry/utils.py
anemoi/registry/commands/__init__.py
anemoi/registry/commands/base.py
anemoi/registry/commands/datasets.py
anemoi/registry/commands/download.py
anemoi/registry/commands/entry.py
anemoi/registry/commands/experiments.py
anemoi/registry/commands/list.py
anemoi/registry/commands/settings.py
anemoi/registry/commands/tasks.py
anemoi/registry/commands/trainings.py
anemoi/registry/commands/update.py
anemoi/registry/commands/update.readme.md
anemoi/registry/commands/upload.py
anemoi/registry/commands/weights.py
anemoi/registry/commands/worker.py
anemoi/registry/entry/__init__.py
anemoi/registry/entry/dataset.py
anemoi/registry/entry/experiment.py
anemoi/registry/entry/training.py
anemoi/registry/entry/weights.py
anemoi/registry/workers/__init__.py
anemoi/registry/workers/delete_dataset.py
anemoi/registry/workers/dummy.py
anemoi/registry/workers/transfer_dataset.py
anemoi_registry-0.2.4.dist-info/licenses/LICENSE
anemoi_registry-0.2.4.dist-info/METADATA
anemoi_registry-0.2.4.dist-info/WHEEL
anemoi_registry-0.2.4.dist-info/entry_points.txt
anemoi_registry-0.2.4.dist-info/top_level.txt
anemoi_registry-0.2.4.dist-info/RECORD
