Metadata-Version: 2.4
Name: anemoi-registry
Version: 0.2.4
Summary: A package to manage a registry or data-driven forecasts.
Author-email: "European Centre for Medium-Range Weather Forecasts (ECMWF)" <software.support@ecmwf.int>
License:                                  Apache License
Project-URL: Documentation, https://anemoi-registry.readthedocs.io/
Project-URL: Homepage, https://github.com/ecmwf/anemoi-registry/
Project-URL: Issues, https://github.com/ecmwf/anemoi-registry/issues
Project-URL: Repository, https://github.com/ecmwf/anemoi-registry/
Keywords: ai,registry,tools
Classifier: Development Status :: 4 - Beta
Classifier: Intended Audience :: Developers
Classifier: License :: OSI Approved :: Apache Software License
Classifier: Operating System :: OS Independent
Classifier: Programming Language :: Python :: 3 :: Only
Classifier: Programming Language :: Python :: 3.10
Classifier: Programming Language :: Python :: 3.11
Classifier: Programming Language :: Python :: 3.12
Classifier: Programming Language :: Python :: Implementation :: CPython
Classifier: Programming Language :: Python :: Implementation :: PyPy
Requires-Python: >=3.10
License-File: LICENSE
Requires-Dist: anemoi-datasets>=0.5.28
Requires-Dist: anemoi-utils[text]>=0.4.39
Requires-Dist: jsonpatch
Requires-Dist: requests
Provides-Extra: all
Requires-Dist: anemoi-utils[s3]; extra == "all"
Provides-Extra: dev
Requires-Dist: anemoi-utils[s3]; extra == "dev"
Requires-Dist: nbsphinx; extra == "dev"
Requires-Dist: pandoc; extra == "dev"
Requires-Dist: pytest; extra == "dev"
Requires-Dist: sphinx; extra == "dev"
Requires-Dist: sphinx-argparse<0.5; extra == "dev"
Requires-Dist: sphinx-rtd-theme; extra == "dev"
Provides-Extra: docs
Requires-Dist: nbsphinx; extra == "docs"
Requires-Dist: pandoc; extra == "docs"
Requires-Dist: sphinx; extra == "docs"
Requires-Dist: sphinx-argparse<0.5; extra == "docs"
Requires-Dist: sphinx-rtd-theme; extra == "docs"
Provides-Extra: s3
Requires-Dist: anemoi-utils[s3]; extra == "s3"
Provides-Extra: tests
Requires-Dist: pytest; extra == "tests"
Dynamic: license-file
